tippisell_api/__init__.py
tippisell_api/client.py
tippisell_api/exceptions.py
tippisell_api/methods.py
tippisell_api/models.py
tippisell_api/webhook.py
tippisell_api-0.6.16.dist-info/METADATA
tippisell_api-0.6.16.dist-info/WHEEL
tippisell_api-0.6.16.dist-info/top_level.txt
tippisell_api-0.6.16.dist-info/RECORD
