Metadata-Version: 2.1
Name: tippisell_api
Version: 0.6.16
Author: alteralt
Project-URL: Source, https://github.com/alteralt/tippisell_api
Classifier: Development Status :: 5 - Production/Stable
Classifier: Intended Audience :: Developers
Classifier: Natural Language :: Russian
Classifier: Programming Language :: Python
Classifier: Programming Language :: Python :: 3.5
Classifier: Programming Language :: Python :: 3.6
Classifier: Programming Language :: Python :: 3.7
Classifier: Programming Language :: Python :: 3.8
Classifier: Programming Language :: Python :: 3.9
Classifier: Programming Language :: Python :: 3.10
Requires-Python: >=3.5
Requires-Dist: aiohttp>=3.6.3
Requires-Dist: pydantic>=1.9.0
